MANIFEST.in
README.rst
setup.cfg
setup.py
micromongo/__init__.py
micromongo/backend.py
micromongo/models.py
micromongo/spec.py
micromongo/utils.py
micromongo.egg-info/PKG-INFO
micromongo.egg-info/SOURCES.txt
micromongo.egg-info/dependency_links.txt
micromongo.egg-info/not-zip-safe
micromongo.egg-info/requires.txt
micromongo.egg-info/top_level.txt