Metadata-Version: 1.0
Name: micromongo
Version: 0.1.4
Summary: small natural object/mongodb driver
Home-page: http://github.com/jmoiron/micromongo
Author: Jason Moiron
Author-email: jmoiron@jmoiron.net
License: MIT
Keywords: mongodb orm
Platform: UNKNOWN
Classifier: Development Status :: 3 - Alpha
Classifier: Topic :: Database :: Front-Ends
Classifier: License :: OSI Approved :: MIT License
Classifier: Intended Audience :: Developers
